monicacrm/#__init__.py#
monicacrm/__init__.py
monicacrm/__init__.py~
monicacrm/__main__.py
monicacrm/__main__.py~
monicacrm/cli.py
monicacrm-0.1.0.dist-info/AUTHORS.md
monicacrm-0.1.0.dist-info/LICENSE
monicacrm-0.1.0.dist-info/METADATA
monicacrm-0.1.0.dist-info/WHEEL
monicacrm-0.1.0.dist-info/entry_points.txt
monicacrm-0.1.0.dist-info/top_level.txt
monicacrm-0.1.0.dist-info/RECORD
