Metadata-Version: 2.1
Name: monicacrm
Version: 0.1.0
Summary: A client library for the MonicaHQ.com personal relationships manager to assist with tasks like bulk import.
Home-page: https://gitlab.com/cathalgarvey/python-monicacrm
Author: Cathal Garvey
Author-email: cathalgarvey@cathalgarvey.me
License: UNKNOWN
Project-URL: Issue Tracker, https://gitlab.com/cathalgarvey/python-monicacrm/issues
Keywords: monica,monicahq,crm,relationships,assistive technology
Platform: UNKNOWN
Classifier: Intended Audience :: Developers
Classifier: Operating System :: Unix
Classifier: Operating System :: POSIX
Classifier: Programming Language :: Python :: 3.6
Classifier: Programming Language :: Python :: 3.7
Classifier: Programming Language :: Python :: Implementation :: CPython
Classifier: Topic :: Utilities
Requires-Python: >=3.6, !=2.7.*, !=3.0.*, !=3.1.*, !=3.2.*, !=3.3.*
Requires-Dist: click
Requires-Dist: requests
